{"nodes":[{"name":"27001325"},{"name":"27001097"},{"name":"FRA"},{"name":"LTU"},{"name":"GBR"},{"name":"IRL"},{"name":"27001998"},{"name":"DNK"},{"name":"NOR"},{"name":"DEU"},{"name":"27000397"},{"name":"SWE"},{"name":"EST"},{"name":"27000229"},{"name":"ESP"}],"links":[{"stockCode":"BLI\/03-","source":9,"value":2.0,"target":6},{"stockCode":"BLI\/24-","source":9,"value":4.0,"target":1},{"stockCode":"BLI\/03-","source":7,"value":4.0,"target":6},{"stockCode":"BLI\/24-","source":7,"value":4.0,"target":1},{"stockCode":"BLI\/12INT-","source":14,"value":832.29,"target":10},{"stockCode":"BLI\/5B67-","source":14,"value":21.07,"target":13},{"stockCode":"BLI\/12INT-","source":12,"value":2.0,"target":10},{"stockCode":"BLI\/12INT-","source":2,"value":21.0,"target":10},{"stockCode":"BLI\/24-","source":2,"value":27.0,"target":1},{"stockCode":"BLI\/5B67-","source":2,"value":1926.4,"target":13},{"stockCode":"BLI\/12INT-","source":4,"value":7.0,"target":10},{"stockCode":"BLI\/24-","source":4,"value":13.0,"target":1},{"stockCode":"BLI\/5B67-","source":4,"value":75.6,"target":13},{"stockCode":"BLI\/24-","source":5,"value":4.0,"target":1},{"stockCode":"BLI\/5B67-","source":5,"value":5.0,"target":13},{"stockCode":"BLI\/12INT-","source":3,"value":7.0,"target":10},{"stockCode":"BLI\/5B67-","source":3,"value":1.0,"target":13},{"stockCode":"BLI\/24X7C","source":8,"value":150.0,"target":0},{"stockCode":"BLI\/5B67-","source":8,"value":150.0,"target":13},{"stockCode":"BLI\/03-","source":11,"value":3.0,"target":6}]}