{"nodes":[{"name":"27000489"},{"name":"27002230"},{"name":"27000311"},{"name":"ROU"},{"name":"FRA"},{"name":"NLD"},{"name":"LTU"},{"name":"GBR"},{"name":"27000045"},{"name":"POL"},{"name":"DNK"},{"name":"NOR"},{"name":"LVA"},{"name":"DEU"},{"name":"SWE"},{"name":"BGR"},{"name":"EST"},{"name":"FIN"},{"name":"37000011"},{"name":"BEL"}],"links":[{"stockCode":"SPR\/2AC4-C","source":19,"value":37.0,"target":2},{"stockCode":"SPR\/7DE.","source":19,"value":26.0,"target":0},{"stockCode":"SPR\/F3742C","source":15,"value":8032.5,"target":18},{"stockCode":"SPR\/03A.","source":13,"value":58.0,"target":8},{"stockCode":"SPR\/2AC4-C","source":13,"value":4538.4,"target":2},{"stockCode":"SPR\/3BCD-C","source":13,"value":10322.0,"target":1},{"stockCode":"SPR\/7DE.","source":13,"value":26.0,"target":0},{"stockCode":"SPR\/03A.","source":10,"value":27875.0,"target":8},{"stockCode":"SPR\/2AC4-C","source":10,"value":132524.0,"target":2},{"stockCode":"SPR\/3BCD-C","source":10,"value":27569.0,"target":1},{"stockCode":"SPR\/7DE.","source":10,"value":656.0,"target":0},{"stockCode":"SPR\/3BCD-C","source":16,"value":29810.0,"target":1},{"stockCode":"SPR\/3BCD-C","source":17,"value":11442.0,"target":1},{"stockCode":"SPR\/2AC4-C","source":4,"value":1737.0,"target":2},{"stockCode":"SPR\/7DE.","source":4,"value":361.0,"target":0},{"stockCode":"SPR\/2AC4-C","source":7,"value":2806.2,"target":2},{"stockCode":"SPR\/7DE.","source":7,"value":4081.0,"target":0},{"stockCode":"SPR\/2AC4-C","source":6,"value":678.0,"target":2},{"stockCode":"SPR\/3BCD-C","source":6,"value":10355.0,"target":1},{"stockCode":"SPR\/3BCD-C","source":12,"value":33310.0,"target":1},{"stockCode":"SPR\/2AC4-C","source":5,"value":4912.4,"target":2},{"stockCode":"SPR\/2AC4-C","source":11,"value":10000.0,"target":2},{"stockCode":"SPR\/3BCD-C","source":9,"value":76680.0,"target":1},{"stockCode":"SPR\/F3742C","source":3,"value":3442.5,"target":18},{"stockCode":"SPR\/03A.","source":14,"value":10547.0,"target":8},{"stockCode":"SPR\/2AC4-C","source":14,"value":4267.0,"target":2},{"stockCode":"SPR\/3BCD-C","source":14,"value":50490.0,"target":1}]}